{
  "id": "I0570",
  "protegida": false,
  "nome": "Quitéria",
  "nome_proprio": "Quitéria",
  "apelido": null,
  "apelidos": null,
  "nomes_alt": null,
  "sexo": "F",
  "nascimento": {
    "data": "1732-05-23",
    "lugar_id": "P0071"
  },
  "baptismo": null,
  "obito": {
    "data": "antes de 1842",
    "lugar_id": null,
    "estimado": true
  },
  "sepultura": null,
  "profissoes": null,
  "familias_como_filho": [
    "F0068"
  ],
  "familias_como_pai": null,
  "media": [
    "O0413"
  ],
  "notas": null,
  "citacoes": null
}