{
  "id": "I0694",
  "protegida": false,
  "nome": "Maria",
  "nome_proprio": "Maria",
  "apelido": null,
  "apelidos": null,
  "nomes_alt": null,
  "sexo": "F",
  "nascimento": {
    "data": "1818-05-12",
    "lugar_id": "P0091"
  },
  "baptismo": null,
  "obito": {
    "data": "antes de 1928",
    "lugar_id": null,
    "estimado": true
  },
  "sepultura": null,
  "profissoes": null,
  "familias_como_filho": [
    "F0203"
  ],
  "familias_como_pai": null,
  "media": [
    "O0565"
  ],
  "notas": null,
  "citacoes": null
}