{
  "id": "I0704",
  "protegida": false,
  "nome": "Maria de Jesus",
  "nome_proprio": "Maria",
  "apelido": "de Jesus",
  "apelidos": null,
  "nomes_alt": null,
  "sexo": "F",
  "nascimento": {
    "data": null,
    "lugar_id": "P0092"
  },
  "baptismo": null,
  "obito": null,
  "sepultura": null,
  "profissoes": null,
  "familias_como_filho": [
    "F0208"
  ],
  "familias_como_pai": [
    "F0206"
  ],
  "media": null,
  "notas": [
    {
      "tipo": "",
      "texto": "procurei pelo óbito, na ortigosa, até 1881"
    }
  ],
  "citacoes": null
}