{
  "id": "I0882",
  "protegida": false,
  "nome": "Francisco",
  "nome_proprio": "Francisco",
  "apelido": null,
  "nomes_alt": null,
  "sexo": "M",
  "nascimento": {
    "data": "1825-02-25",
    "lugar_id": "P0076"
  },
  "baptismo": null,
  "obito": {
    "data": "1826-03-29",
    "lugar_id": "P0076"
  },
  "sepultura": null,
  "profissao": null,
  "familias_como_filho": [
    "F0242"
  ],
  "familias_como_pai": null,
  "media": [
    "O0733",
    "O0748"
  ],
  "notas": null,
  "citacoes": null
}